README.txt
setup.py
xml_compare.py
xml_compare.egg-info/PKG-INFO
xml_compare.egg-info/SOURCES.txt
xml_compare.egg-info/dependency_links.txt
xml_compare.egg-info/requires.txt
xml_compare.egg-info/top_level.txt