Metadata-Version: 1.0
Name: xml-compare
Version: 1.0.5
Summary: xml_compare is a XML tree comparer.
Home-page: UNKNOWN
Author: Marijn Vriens
Author-email: marijn+xmlcompare@metronomo.cl
License: BSD
Keywords: xml compare library testing
Platform: UNKNOWN
Classifier: Development Status :: 5 - Production/Stable
Classifier: Intended Audience :: Developers
Classifier: License :: OSI Approved :: BSD License
Classifier: Programming Language :: Python
Classifier: Topic :: Software Development :: Libraries
Classifier: Topic :: Software Development :: Testing
Classifier: Topic :: Text Processing :: Markup :: XML
